{
  "ignorePaths": [
    "**/node_modules/**",
    "**/vscode-extension/**",
    "**/.git/**",
    ".vscode",
    "megalinter",
    "*.yml",
    "*.yaml",
    "**/requirements.txt"
  ],
  "words": [
    "backframe",
    "baudrate",
    "BEGA",
    "DAPC",
    "devicetype",
    "ETIMEDOUT",
    "ENODEV",
    "gitmodules",
    "GTIN",
    "Hädrich",
    "Haedrich",
    "initialisation",
    "istatus",
    "Lunatone",
    "membank",
    "portname",
    "pytest",
    "PYTHONPATH",
    "randomise",
    "SEARCHADDRH",
    "SEARCHADDRL",
    "SEARCHADDRM",
    "setuptools",
    "Sven",
    "testframe",
    "ungroup",
    "usec",
    "venv"
  ],
  "language": "en",
  "noConfigSearch": true,
  "version": "0.2"
}
